{
  "type": "File",
  "start": 0,
  "end": 540,
  "loc": {
    "start": {
      "line": 1,
      "column": 0
    },
    "end": {
      "line": 26,
      "column": 0
    }
  },
  "program": {
    "type": "Program",
    "start": 0,
    "end": 540,
    "loc": {
      "start": {
        "line": 1,
        "column": 0
      },
      "end": {
        "line": 26,
        "column": 0
      }
    },
    "sourceType": "module",
    "body": [
      {
        "type": "ImportDeclaration",
        "start": 0,
        "end": 50,
        "loc": {
          "start": {
            "line": 1,
            "column": 0
          },
          "end": {
            "line": 1,
            "column": 50
          }
        },
        "specifiers": [
          {
            "type": "ImportSpecifier",
            "start": 9,
            "end": 23,
            "loc": {
              "start": {
                "line": 1,
                "column": 9
              },
              "end": {
                "line": 1,
                "column": 23
              }
            },
            "imported": {
              "type": "Identifier",
              "start": 9,
              "end": 23,
              "loc": {
                "start": {
                  "line": 1,
                  "column": 9
                },
                "end": {
                  "line": 1,
                  "column": 23
                },
                "identifierName": "PatternMatcher"
              },
              "name": "PatternMatcher"
            },
            "local": {
              "type": "Identifier",
              "start": 9,
              "end": 23,
              "loc": {
                "start": {
                  "line": 1,
                  "column": 9
                },
                "end": {
                  "line": 1,
                  "column": 23
                },
                "identifierName": "PatternMatcher"
              },
              "name": "PatternMatcher"
            }
          }
        ],
        "source": {
          "type": "StringLiteral",
          "start": 31,
          "end": 49,
          "loc": {
            "start": {
              "line": 1,
              "column": 31
            },
            "end": {
              "line": 1,
              "column": 49
            }
          },
          "extra": {
            "rawValue": "./PatternMatcher",
            "raw": "'./PatternMatcher'"
          },
          "value": "./PatternMatcher"
        }
      },
      {
        "type": "ImportDeclaration",
        "start": 51,
        "end": 94,
        "loc": {
          "start": {
            "line": 2,
            "column": 0
          },
          "end": {
            "line": 2,
            "column": 43
          }
        },
        "specifiers": [
          {
            "type": "ImportSpecifier",
            "start": 60,
            "end": 76,
            "loc": {
              "start": {
                "line": 2,
                "column": 9
              },
              "end": {
                "line": 2,
                "column": 25
              }
            },
            "imported": {
              "type": "Identifier",
              "start": 60,
              "end": 76,
              "loc": {
                "start": {
                  "line": 2,
                  "column": 9
                },
                "end": {
                  "line": 2,
                  "column": 25
                },
                "identifierName": "MatchesIdentical"
              },
              "name": "MatchesIdentical"
            },
            "local": {
              "type": "Identifier",
              "start": 60,
              "end": 76,
              "loc": {
                "start": {
                  "line": 2,
                  "column": 9
                },
                "end": {
                  "line": 2,
                  "column": 25
                },
                "identifierName": "MatchesIdentical"
              },
              "name": "MatchesIdentical"
            }
          }
        ],
        "source": {
          "type": "StringLiteral",
          "start": 84,
          "end": 93,
          "loc": {
            "start": {
              "line": 2,
              "column": 33
            },
            "end": {
              "line": 2,
              "column": 42
            }
          },
          "extra": {
            "rawValue": "./rules",
            "raw": "'./rules'"
          },
          "value": "./rules"
        },
        "trailingComments": [
          {
            "type": "CommentBlock",
            "value": "*\n * @desc\n *\n * @lineNumber\n * 4\n ",
            "start": 95,
            "end": 134,
            "loc": {
              "start": {
                "line": 3,
                "column": 0
              },
              "end": {
                "line": 8,
                "column": 3
              }
            }
          }
        ]
      },
      {
        "type": "ExportNamedDeclaration",
        "start": 135,
        "end": 539,
        "loc": {
          "start": {
            "line": 9,
            "column": 0
          },
          "end": {
            "line": 25,
            "column": 1
          }
        },
        "specifiers": [],
        "source": null,
        "declaration": {
          "type": "ClassDeclaration",
          "start": 142,
          "end": 539,
          "loc": {
            "start": {
              "line": 9,
              "column": 7
            },
            "end": {
              "line": 25,
              "column": 1
            }
          },
          "id": {
            "type": "Identifier",
            "start": 148,
            "end": 163,
            "loc": {
              "start": {
                "line": 9,
                "column": 13
              },
              "end": {
                "line": 9,
                "column": 28
              },
              "identifierName": "IdentityMatcher"
            },
            "name": "IdentityMatcher",
            "leadingComments": null
          },
          "superClass": {
            "type": "Identifier",
            "start": 172,
            "end": 186,
            "loc": {
              "start": {
                "line": 9,
                "column": 37
              },
              "end": {
                "line": 9,
                "column": 51
              },
              "identifierName": "PatternMatcher"
            },
            "name": "PatternMatcher"
          },
          "body": {
            "type": "ClassBody",
            "start": 187,
            "end": 539,
            "loc": {
              "start": {
                "line": 9,
                "column": 52
              },
              "end": {
                "line": 25,
                "column": 1
              }
            },
            "body": [
              {
                "type": "ClassMethod",
                "start": 386,
                "end": 537,
                "loc": {
                  "start": {
                    "line": 22,
                    "column": 4
                  },
                  "end": {
                    "line": 24,
                    "column": 5
                  }
                },
                "static": false,
                "computed": false,
                "key": {
                  "type": "Identifier",
                  "start": 386,
                  "end": 390,
                  "loc": {
                    "start": {
                      "line": 22,
                      "column": 4
                    },
                    "end": {
                      "line": 22,
                      "column": 8
                    },
                    "identifierName": "when"
                  },
                  "name": "when",
                  "leadingComments": null
                },
                "kind": "method",
                "id": null,
                "generator": false,
                "expression": false,
                "async": false,
                "params": [
                  {
                    "type": "Identifier",
                    "start": 391,
                    "end": 398,
                    "loc": {
                      "start": {
                        "line": 22,
                        "column": 9
                      },
                      "end": {
                        "line": 22,
                        "column": 16
                      },
                      "identifierName": "pattern"
                    },
                    "name": "pattern"
                  },
                  {
                    "type": "Identifier",
                    "start": 400,
                    "end": 414,
                    "loc": {
                      "start": {
                        "line": 22,
                        "column": 18
                      },
                      "end": {
                        "line": 22,
                        "column": 32
                      },
                      "identifierName": "transformation"
                    },
                    "name": "transformation"
                  }
                ],
                "body": {
                  "type": "BlockStatement",
                  "start": 416,
                  "end": 537,
                  "loc": {
                    "start": {
                      "line": 22,
                      "column": 34
                    },
                    "end": {
                      "line": 24,
                      "column": 5
                    }
                  },
                  "body": [
                    {
                      "type": "ReturnStatement",
                      "start": 426,
                      "end": 531,
                      "loc": {
                        "start": {
                          "line": 23,
                          "column": 8
                        },
                        "end": {
                          "line": 23,
                          "column": 113
                        }
                      },
                      "argument": {
                        "type": "NewExpression",
                        "start": 433,
                        "end": 530,
                        "loc": {
                          "start": {
                            "line": 23,
                            "column": 15
                          },
                          "end": {
                            "line": 23,
                            "column": 112
                          }
                        },
                        "callee": {
                          "type": "Identifier",
                          "start": 437,
                          "end": 452,
                          "loc": {
                            "start": {
                              "line": 23,
                              "column": 19
                            },
                            "end": {
                              "line": 23,
                              "column": 34
                            },
                            "identifierName": "IdentityMatcher"
                          },
                          "name": "IdentityMatcher"
                        },
                        "arguments": [
                          {
                            "type": "MemberExpression",
                            "start": 453,
                            "end": 463,
                            "loc": {
                              "start": {
                                "line": 23,
                                "column": 35
                              },
                              "end": {
                                "line": 23,
                                "column": 45
                              }
                            },
                            "object": {
                              "type": "ThisExpression",
                              "start": 453,
                              "end": 457,
                              "loc": {
                                "start": {
                                  "line": 23,
                                  "column": 35
                                },
                                "end": {
                                  "line": 23,
                                  "column": 39
                                }
                              }
                            },
                            "property": {
                              "type": "Identifier",
                              "start": 458,
                              "end": 463,
                              "loc": {
                                "start": {
                                  "line": 23,
                                  "column": 40
                                },
                                "end": {
                                  "line": 23,
                                  "column": 45
                                },
                                "identifierName": "value"
                              },
                              "name": "value"
                            },
                            "computed": false
                          },
                          {
                            "type": "CallExpression",
                            "start": 465,
                            "end": 529,
                            "loc": {
                              "start": {
                                "line": 23,
                                "column": 47
                              },
                              "end": {
                                "line": 23,
                                "column": 111
                              }
                            },
                            "callee": {
                              "type": "MemberExpression",
                              "start": 465,
                              "end": 482,
                              "loc": {
                                "start": {
                                  "line": 23,
                                  "column": 47
                                },
                                "end": {
                                  "line": 23,
                                  "column": 64
                                }
                              },
                              "object": {
                                "type": "MemberExpression",
                                "start": 465,
                                "end": 475,
                                "loc": {
                                  "start": {
                                    "line": 23,
                                    "column": 47
                                  },
                                  "end": {
                                    "line": 23,
                                    "column": 57
                                  }
                                },
                                "object": {
                                  "type": "ThisExpression",
                                  "start": 465,
                                  "end": 469,
                                  "loc": {
                                    "start": {
                                      "line": 23,
                                      "column": 47
                                    },
                                    "end": {
                                      "line": 23,
                                      "column": 51
                                    }
                                  }
                                },
                                "property": {
                                  "type": "Identifier",
                                  "start": 470,
                                  "end": 475,
                                  "loc": {
                                    "start": {
                                      "line": 23,
                                      "column": 52
                                    },
                                    "end": {
                                      "line": 23,
                                      "column": 57
                                    },
                                    "identifierName": "rules"
                                  },
                                  "name": "rules"
                                },
                                "computed": false
                              },
                              "property": {
                                "type": "Identifier",
                                "start": 476,
                                "end": 482,
                                "loc": {
                                  "start": {
                                    "line": 23,
                                    "column": 58
                                  },
                                  "end": {
                                    "line": 23,
                                    "column": 64
                                  },
                                  "identifierName": "concat"
                                },
                                "name": "concat"
                              },
                              "computed": false
                            },
                            "arguments": [
                              {
                                "type": "NewExpression",
                                "start": 483,
                                "end": 528,
                                "loc": {
                                  "start": {
                                    "line": 23,
                                    "column": 65
                                  },
                                  "end": {
                                    "line": 23,
                                    "column": 110
                                  }
                                },
                                "callee": {
                                  "type": "Identifier",
                                  "start": 487,
                                  "end": 503,
                                  "loc": {
                                    "start": {
                                      "line": 23,
                                      "column": 69
                                    },
                                    "end": {
                                      "line": 23,
                                      "column": 85
                                    },
                                    "identifierName": "MatchesIdentical"
                                  },
                                  "name": "MatchesIdentical"
                                },
                                "arguments": [
                                  {
                                    "type": "Identifier",
                                    "start": 504,
                                    "end": 511,
                                    "loc": {
                                      "start": {
                                        "line": 23,
                                        "column": 86
                                      },
                                      "end": {
                                        "line": 23,
                                        "column": 93
                                      },
                                      "identifierName": "pattern"
                                    },
                                    "name": "pattern"
                                  },
                                  {
                                    "type": "Identifier",
                                    "start": 513,
                                    "end": 527,
                                    "loc": {
                                      "start": {
                                        "line": 23,
                                        "column": 95
                                      },
                                      "end": {
                                        "line": 23,
                                        "column": 109
                                      },
                                      "identifierName": "transformation"
                                    },
                                    "name": "transformation"
                                  }
                                ]
                              }
                            ]
                          }
                        ]
                      }
                    }
                  ],
                  "directives": []
                },
                "leadingComments": [
                  {
                    "type": "CommentBlock",
                    "value": "*\n     * @desc\n     *\n     * @lineNumber\n     * 6\n     * @param\n     * {Input_Type} pattern\n     * @param\n     * {undefined} transformation\n     * @return\n     * {PatternMatcher}\n     ",
                    "start": 193,
                    "end": 381,
                    "loc": {
                      "start": {
                        "line": 10,
                        "column": 4
                      },
                      "end": {
                        "line": 21,
                        "column": 7
                      }
                    }
                  }
                ]
              }
            ]
          },
          "leadingComments": [
            {
              "type": "CommentBlock",
              "value": "*\n * @desc\n *\n * @lineNumber\n * 4\n ",
              "start": 95,
              "end": 134,
              "loc": {
                "start": {
                  "line": 3,
                  "column": 0
                },
                "end": {
                  "line": 8,
                  "column": 3
                }
              }
            }
          ],
          "trailingComments": []
        },
        "leadingComments": [
          {
            "type": "CommentBlock",
            "value": "*\n * @desc\n *\n * @lineNumber\n * 4\n ",
            "start": 95,
            "end": 134,
            "loc": {
              "start": {
                "line": 3,
                "column": 0
              },
              "end": {
                "line": 8,
                "column": 3
              }
            }
          }
        ]
      }
    ],
    "directives": []
  },
  "comments": [
    {
      "type": "CommentBlock",
      "value": "*\n * @desc\n *\n * @lineNumber\n * 4\n ",
      "start": 95,
      "end": 134,
      "loc": {
        "start": {
          "line": 3,
          "column": 0
        },
        "end": {
          "line": 8,
          "column": 3
        }
      }
    },
    {
      "type": "CommentBlock",
      "value": "*\n     * @desc\n     *\n     * @lineNumber\n     * 6\n     * @param\n     * {Input_Type} pattern\n     * @param\n     * {undefined} transformation\n     * @return\n     * {PatternMatcher}\n     ",
      "start": 193,
      "end": 381,
      "loc": {
        "start": {
          "line": 10,
          "column": 4
        },
        "end": {
          "line": 21,
          "column": 7
        }
      }
    }
  ],
  "tokens": [
    {
      "type": {
        "label": "import",
        "keyword": "import",
        "beforeExpr": false,
        "startsExpr": true,
        "rightAssociative": false,
        "isLoop": false,
        "isAssign": false,
        "prefix": false,
        "postfix": false,
        "binop": null,
        "updateContext": null
      },
      "value": "import",
      "start": 0,
      "end": 6,
      "loc": {
        "start": {
          "line": 1,
          "column": 0
        },
        "end": {
          "line": 1,
          "column": 6
        }
      }
    },
    {
      "type": {
        "label": "{",
        "beforeExpr": true,
        "startsExpr": true,
        "rightAssociative": false,
        "isLoop": false,
        "isAssign": false,
        "prefix": false,
        "postfix": false,
        "binop": null
      },
      "start": 7,
      "end": 8,
      "loc": {
        "start": {
          "line": 1,
          "column": 7
        },
        "end": {
          "line": 1,
          "column": 8
        }
      }
    },
    {
      "type": {
        "label": "name",
        "beforeExpr": false,
        "startsExpr": true,
        "rightAssociative": false,
        "isLoop": false,
        "isAssign": false,
        "prefix": false,
        "postfix": false,
        "binop": null
      },
      "value": "PatternMatcher",
      "start": 9,
      "end": 23,
      "loc": {
        "start": {
          "line": 1,
          "column": 9
        },
        "end": {
          "line": 1,
          "column": 23
        }
      }
    },
    {
      "type": {
        "label": "}",
        "beforeExpr": false,
        "startsExpr": false,
        "rightAssociative": false,
        "isLoop": false,
        "isAssign": false,
        "prefix": false,
        "postfix": false,
        "binop": null
      },
      "start": 24,
      "end": 25,
      "loc": {
        "start": {
          "line": 1,
          "column": 24
        },
        "end": {
          "line": 1,
          "column": 25
        }
      }
    },
    {
      "type": {
        "label": "name",
        "beforeExpr": false,
        "startsExpr": true,
        "rightAssociative": false,
        "isLoop": false,
        "isAssign": false,
        "prefix": false,
        "postfix": false,
        "binop": null
      },
      "value": "from",
      "start": 26,
      "end": 30,
      "loc": {
        "start": {
          "line": 1,
          "column": 26
        },
        "end": {
          "line": 1,
          "column": 30
        }
      }
    },
    {
      "type": {
        "label": "string",
        "beforeExpr": false,
        "startsExpr": true,
        "rightAssociative": false,
        "isLoop": false,
        "isAssign": false,
        "prefix": false,
        "postfix": false,
        "binop": null,
        "updateContext": null
      },
      "value": "./PatternMatcher",
      "start": 31,
      "end": 49,
      "loc": {
        "start": {
          "line": 1,
          "column": 31
        },
        "end": {
          "line": 1,
          "column": 49
        }
      }
    },
    {
      "type": {
        "label": ";",
        "beforeExpr": true,
        "startsExpr": false,
        "rightAssociative": false,
        "isLoop": false,
        "isAssign": false,
        "prefix": false,
        "postfix": false,
        "binop": null,
        "updateContext": null
      },
      "start": 49,
      "end": 50,
      "loc": {
        "start": {
          "line": 1,
          "column": 49
        },
        "end": {
          "line": 1,
          "column": 50
        }
      }
    },
    {
      "type": {
        "label": "import",
        "keyword": "import",
        "beforeExpr": false,
        "startsExpr": true,
        "rightAssociative": false,
        "isLoop": false,
        "isAssign": false,
        "prefix": false,
        "postfix": false,
        "binop": null,
        "updateContext": null
      },
      "value": "import",
      "start": 51,
      "end": 57,
      "loc": {
        "start": {
          "line": 2,
          "column": 0
        },
        "end": {
          "line": 2,
          "column": 6
        }
      }
    },
    {
      "type": {
        "label": "{",
        "beforeExpr": true,
        "startsExpr": true,
        "rightAssociative": false,
        "isLoop": false,
        "isAssign": false,
        "prefix": false,
        "postfix": false,
        "binop": null
      },
      "start": 58,
      "end": 59,
      "loc": {
        "start": {
          "line": 2,
          "column": 7
        },
        "end": {
          "line": 2,
          "column": 8
        }
      }
    },
    {
      "type": {
        "label": "name",
        "beforeExpr": false,
        "startsExpr": true,
        "rightAssociative": false,
        "isLoop": false,
        "isAssign": false,
        "prefix": false,
        "postfix": false,
        "binop": null
      },
      "value": "MatchesIdentical",
      "start": 60,
      "end": 76,
      "loc": {
        "start": {
          "line": 2,
          "column": 9
        },
        "end": {
          "line": 2,
          "column": 25
        }
      }
    },
    {
      "type": {
        "label": "}",
        "beforeExpr": false,
        "startsExpr": false,
        "rightAssociative": false,
        "isLoop": false,
        "isAssign": false,
        "prefix": false,
        "postfix": false,
        "binop": null
      },
      "start": 77,
      "end": 78,
      "loc": {
        "start": {
          "line": 2,
          "column": 26
        },
        "end": {
          "line": 2,
          "column": 27
        }
      }
    },
    {
      "type": {
        "label": "name",
        "beforeExpr": false,
        "startsExpr": true,
        "rightAssociative": false,
        "isLoop": false,
        "isAssign": false,
        "prefix": false,
        "postfix": false,
        "binop": null
      },
      "value": "from",
      "start": 79,
      "end": 83,
      "loc": {
        "start": {
          "line": 2,
          "column": 28
        },
        "end": {
          "line": 2,
          "column": 32
        }
      }
    },
    {
      "type": {
        "label": "string",
        "beforeExpr": false,
        "startsExpr": true,
        "rightAssociative": false,
        "isLoop": false,
        "isAssign": false,
        "prefix": false,
        "postfix": false,
        "binop": null,
        "updateContext": null
      },
      "value": "./rules",
      "start": 84,
      "end": 93,
      "loc": {
        "start": {
          "line": 2,
          "column": 33
        },
        "end": {
          "line": 2,
          "column": 42
        }
      }
    },
    {
      "type": {
        "label": ";",
        "beforeExpr": true,
        "startsExpr": false,
        "rightAssociative": false,
        "isLoop": false,
        "isAssign": false,
        "prefix": false,
        "postfix": false,
        "binop": null,
        "updateContext": null
      },
      "start": 93,
      "end": 94,
      "loc": {
        "start": {
          "line": 2,
          "column": 42
        },
        "end": {
          "line": 2,
          "column": 43
        }
      }
    },
    {
      "type": "CommentBlock",
      "value": "*\n * @desc\n *\n * @lineNumber\n * 4\n ",
      "start": 95,
      "end": 134,
      "loc": {
        "start": {
          "line": 3,
          "column": 0
        },
        "end": {
          "line": 8,
          "column": 3
        }
      }
    },
    {
      "type": {
        "label": "export",
        "keyword": "export",
        "beforeExpr": false,
        "startsExpr": false,
        "rightAssociative": false,
        "isLoop": false,
        "isAssign": false,
        "prefix": false,
        "postfix": false,
        "binop": null,
        "updateContext": null
      },
      "value": "export",
      "start": 135,
      "end": 141,
      "loc": {
        "start": {
          "line": 9,
          "column": 0
        },
        "end": {
          "line": 9,
          "column": 6
        }
      }
    },
    {
      "type": {
        "label": "class",
        "keyword": "class",
        "beforeExpr": false,
        "startsExpr": false,
        "rightAssociative": false,
        "isLoop": false,
        "isAssign": false,
        "prefix": false,
        "postfix": false,
        "binop": null,
        "updateContext": null
      },
      "value": "class",
      "start": 142,
      "end": 147,
      "loc": {
        "start": {
          "line": 9,
          "column": 7
        },
        "end": {
          "line": 9,
          "column": 12
        }
      }
    },
    {
      "type": {
        "label": "name",
        "beforeExpr": false,
        "startsExpr": true,
        "rightAssociative": false,
        "isLoop": false,
        "isAssign": false,
        "prefix": false,
        "postfix": false,
        "binop": null
      },
      "value": "IdentityMatcher",
      "start": 148,
      "end": 163,
      "loc": {
        "start": {
          "line": 9,
          "column": 13
        },
        "end": {
          "line": 9,
          "column": 28
        }
      }
    },
    {
      "type": {
        "label": "extends",
        "keyword": "extends",
        "beforeExpr": true,
        "startsExpr": false,
        "rightAssociative": false,
        "isLoop": false,
        "isAssign": false,
        "prefix": false,
        "postfix": false,
        "binop": null,
        "updateContext": null
      },
      "value": "extends",
      "start": 164,
      "end": 171,
      "loc": {
        "start": {
          "line": 9,
          "column": 29
        },
        "end": {
          "line": 9,
          "column": 36
        }
      }
    },
    {
      "type": {
        "label": "name",
        "beforeExpr": false,
        "startsExpr": true,
        "rightAssociative": false,
        "isLoop": false,
        "isAssign": false,
        "prefix": false,
        "postfix": false,
        "binop": null
      },
      "value": "PatternMatcher",
      "start": 172,
      "end": 186,
      "loc": {
        "start": {
          "line": 9,
          "column": 37
        },
        "end": {
          "line": 9,
          "column": 51
        }
      }
    },
    {
      "type": {
        "label": "{",
        "beforeExpr": true,
        "startsExpr": true,
        "rightAssociative": false,
        "isLoop": false,
        "isAssign": false,
        "prefix": false,
        "postfix": false,
        "binop": null
      },
      "start": 187,
      "end": 188,
      "loc": {
        "start": {
          "line": 9,
          "column": 52
        },
        "end": {
          "line": 9,
          "column": 53
        }
      }
    },
    {
      "type": "CommentBlock",
      "value": "*\n     * @desc\n     *\n     * @lineNumber\n     * 6\n     * @param\n     * {Input_Type} pattern\n     * @param\n     * {undefined} transformation\n     * @return\n     * {PatternMatcher}\n     ",
      "start": 193,
      "end": 381,
      "loc": {
        "start": {
          "line": 10,
          "column": 4
        },
        "end": {
          "line": 21,
          "column": 7
        }
      }
    },
    {
      "type": {
        "label": "name",
        "beforeExpr": false,
        "startsExpr": true,
        "rightAssociative": false,
        "isLoop": false,
        "isAssign": false,
        "prefix": false,
        "postfix": false,
        "binop": null
      },
      "value": "when",
      "start": 386,
      "end": 390,
      "loc": {
        "start": {
          "line": 22,
          "column": 4
        },
        "end": {
          "line": 22,
          "column": 8
        }
      }
    },
    {
      "type": {
        "label": "(",
        "beforeExpr": true,
        "startsExpr": true,
        "rightAssociative": false,
        "isLoop": false,
        "isAssign": false,
        "prefix": false,
        "postfix": false,
        "binop": null
      },
      "start": 390,
      "end": 391,
      "loc": {
        "start": {
          "line": 22,
          "column": 8
        },
        "end": {
          "line": 22,
          "column": 9
        }
      }
    },
    {
      "type": {
        "label": "name",
        "beforeExpr": false,
        "startsExpr": true,
        "rightAssociative": false,
        "isLoop": false,
        "isAssign": false,
        "prefix": false,
        "postfix": false,
        "binop": null
      },
      "value": "pattern",
      "start": 391,
      "end": 398,
      "loc": {
        "start": {
          "line": 22,
          "column": 9
        },
        "end": {
          "line": 22,
          "column": 16
        }
      }
    },
    {
      "type": {
        "label": ",",
        "beforeExpr": true,
        "startsExpr": false,
        "rightAssociative": false,
        "isLoop": false,
        "isAssign": false,
        "prefix": false,
        "postfix": false,
        "binop": null,
        "updateContext": null
      },
      "start": 398,
      "end": 399,
      "loc": {
        "start": {
          "line": 22,
          "column": 16
        },
        "end": {
          "line": 22,
          "column": 17
        }
      }
    },
    {
      "type": {
        "label": "name",
        "beforeExpr": false,
        "startsExpr": true,
        "rightAssociative": false,
        "isLoop": false,
        "isAssign": false,
        "prefix": false,
        "postfix": false,
        "binop": null
      },
      "value": "transformation",
      "start": 400,
      "end": 414,
      "loc": {
        "start": {
          "line": 22,
          "column": 18
        },
        "end": {
          "line": 22,
          "column": 32
        }
      }
    },
    {
      "type": {
        "label": ")",
        "beforeExpr": false,
        "startsExpr": false,
        "rightAssociative": false,
        "isLoop": false,
        "isAssign": false,
        "prefix": false,
        "postfix": false,
        "binop": null
      },
      "start": 414,
      "end": 415,
      "loc": {
        "start": {
          "line": 22,
          "column": 32
        },
        "end": {
          "line": 22,
          "column": 33
        }
      }
    },
    {
      "type": {
        "label": "{",
        "beforeExpr": true,
        "startsExpr": true,
        "rightAssociative": false,
        "isLoop": false,
        "isAssign": false,
        "prefix": false,
        "postfix": false,
        "binop": null
      },
      "start": 416,
      "end": 417,
      "loc": {
        "start": {
          "line": 22,
          "column": 34
        },
        "end": {
          "line": 22,
          "column": 35
        }
      }
    },
    {
      "type": {
        "label": "return",
        "keyword": "return",
        "beforeExpr": true,
        "startsExpr": false,
        "rightAssociative": false,
        "isLoop": false,
        "isAssign": false,
        "prefix": false,
        "postfix": false,
        "binop": null,
        "updateContext": null
      },
      "value": "return",
      "start": 426,
      "end": 432,
      "loc": {
        "start": {
          "line": 23,
          "column": 8
        },
        "end": {
          "line": 23,
          "column": 14
        }
      }
    },
    {
      "type": {
        "label": "new",
        "keyword": "new",
        "beforeExpr": true,
        "startsExpr": true,
        "rightAssociative": false,
        "isLoop": false,
        "isAssign": false,
        "prefix": false,
        "postfix": false,
        "binop": null,
        "updateContext": null
      },
      "value": "new",
      "start": 433,
      "end": 436,
      "loc": {
        "start": {
          "line": 23,
          "column": 15
        },
        "end": {
          "line": 23,
          "column": 18
        }
      }
    },
    {
      "type": {
        "label": "name",
        "beforeExpr": false,
        "startsExpr": true,
        "rightAssociative": false,
        "isLoop": false,
        "isAssign": false,
        "prefix": false,
        "postfix": false,
        "binop": null
      },
      "value": "IdentityMatcher",
      "start": 437,
      "end": 452,
      "loc": {
        "start": {
          "line": 23,
          "column": 19
        },
        "end": {
          "line": 23,
          "column": 34
        }
      }
    },
    {
      "type": {
        "label": "(",
        "beforeExpr": true,
        "startsExpr": true,
        "rightAssociative": false,
        "isLoop": false,
        "isAssign": false,
        "prefix": false,
        "postfix": false,
        "binop": null
      },
      "start": 452,
      "end": 453,
      "loc": {
        "start": {
          "line": 23,
          "column": 34
        },
        "end": {
          "line": 23,
          "column": 35
        }
      }
    },
    {
      "type": {
        "label": "this",
        "keyword": "this",
        "beforeExpr": false,
        "startsExpr": true,
        "rightAssociative": false,
        "isLoop": false,
        "isAssign": false,
        "prefix": false,
        "postfix": false,
        "binop": null,
        "updateContext": null
      },
      "value": "this",
      "start": 453,
      "end": 457,
      "loc": {
        "start": {
          "line": 23,
          "column": 35
        },
        "end": {
          "line": 23,
          "column": 39
        }
      }
    },
    {
      "type": {
        "label": ".",
        "beforeExpr": false,
        "startsExpr": false,
        "rightAssociative": false,
        "isLoop": false,
        "isAssign": false,
        "prefix": false,
        "postfix": false,
        "binop": null,
        "updateContext": null
      },
      "start": 457,
      "end": 458,
      "loc": {
        "start": {
          "line": 23,
          "column": 39
        },
        "end": {
          "line": 23,
          "column": 40
        }
      }
    },
    {
      "type": {
        "label": "name",
        "beforeExpr": false,
        "startsExpr": true,
        "rightAssociative": false,
        "isLoop": false,
        "isAssign": false,
        "prefix": false,
        "postfix": false,
        "binop": null
      },
      "value": "value",
      "start": 458,
      "end": 463,
      "loc": {
        "start": {
          "line": 23,
          "column": 40
        },
        "end": {
          "line": 23,
          "column": 45
        }
      }
    },
    {
      "type": {
        "label": ",",
        "beforeExpr": true,
        "startsExpr": false,
        "rightAssociative": false,
        "isLoop": false,
        "isAssign": false,
        "prefix": false,
        "postfix": false,
        "binop": null,
        "updateContext": null
      },
      "start": 463,
      "end": 464,
      "loc": {
        "start": {
          "line": 23,
          "column": 45
        },
        "end": {
          "line": 23,
          "column": 46
        }
      }
    },
    {
      "type": {
        "label": "this",
        "keyword": "this",
        "beforeExpr": false,
        "startsExpr": true,
        "rightAssociative": false,
        "isLoop": false,
        "isAssign": false,
        "prefix": false,
        "postfix": false,
        "binop": null,
        "updateContext": null
      },
      "value": "this",
      "start": 465,
      "end": 469,
      "loc": {
        "start": {
          "line": 23,
          "column": 47
        },
        "end": {
          "line": 23,
          "column": 51
        }
      }
    },
    {
      "type": {
        "label": ".",
        "beforeExpr": false,
        "startsExpr": false,
        "rightAssociative": false,
        "isLoop": false,
        "isAssign": false,
        "prefix": false,
        "postfix": false,
        "binop": null,
        "updateContext": null
      },
      "start": 469,
      "end": 470,
      "loc": {
        "start": {
          "line": 23,
          "column": 51
        },
        "end": {
          "line": 23,
          "column": 52
        }
      }
    },
    {
      "type": {
        "label": "name",
        "beforeExpr": false,
        "startsExpr": true,
        "rightAssociative": false,
        "isLoop": false,
        "isAssign": false,
        "prefix": false,
        "postfix": false,
        "binop": null
      },
      "value": "rules",
      "start": 470,
      "end": 475,
      "loc": {
        "start": {
          "line": 23,
          "column": 52
        },
        "end": {
          "line": 23,
          "column": 57
        }
      }
    },
    {
      "type": {
        "label": ".",
        "beforeExpr": false,
        "startsExpr": false,
        "rightAssociative": false,
        "isLoop": false,
        "isAssign": false,
        "prefix": false,
        "postfix": false,
        "binop": null,
        "updateContext": null
      },
      "start": 475,
      "end": 476,
      "loc": {
        "start": {
          "line": 23,
          "column": 57
        },
        "end": {
          "line": 23,
          "column": 58
        }
      }
    },
    {
      "type": {
        "label": "name",
        "beforeExpr": false,
        "startsExpr": true,
        "rightAssociative": false,
        "isLoop": false,
        "isAssign": false,
        "prefix": false,
        "postfix": false,
        "binop": null
      },
      "value": "concat",
      "start": 476,
      "end": 482,
      "loc": {
        "start": {
          "line": 23,
          "column": 58
        },
        "end": {
          "line": 23,
          "column": 64
        }
      }
    },
    {
      "type": {
        "label": "(",
        "beforeExpr": true,
        "startsExpr": true,
        "rightAssociative": false,
        "isLoop": false,
        "isAssign": false,
        "prefix": false,
        "postfix": false,
        "binop": null
      },
      "start": 482,
      "end": 483,
      "loc": {
        "start": {
          "line": 23,
          "column": 64
        },
        "end": {
          "line": 23,
          "column": 65
        }
      }
    },
    {
      "type": {
        "label": "new",
        "keyword": "new",
        "beforeExpr": true,
        "startsExpr": true,
        "rightAssociative": false,
        "isLoop": false,
        "isAssign": false,
        "prefix": false,
        "postfix": false,
        "binop": null,
        "updateContext": null
      },
      "value": "new",
      "start": 483,
      "end": 486,
      "loc": {
        "start": {
          "line": 23,
          "column": 65
        },
        "end": {
          "line": 23,
          "column": 68
        }
      }
    },
    {
      "type": {
        "label": "name",
        "beforeExpr": false,
        "startsExpr": true,
        "rightAssociative": false,
        "isLoop": false,
        "isAssign": false,
        "prefix": false,
        "postfix": false,
        "binop": null
      },
      "value": "MatchesIdentical",
      "start": 487,
      "end": 503,
      "loc": {
        "start": {
          "line": 23,
          "column": 69
        },
        "end": {
          "line": 23,
          "column": 85
        }
      }
    },
    {
      "type": {
        "label": "(",
        "beforeExpr": true,
        "startsExpr": true,
        "rightAssociative": false,
        "isLoop": false,
        "isAssign": false,
        "prefix": false,
        "postfix": false,
        "binop": null
      },
      "start": 503,
      "end": 504,
      "loc": {
        "start": {
          "line": 23,
          "column": 85
        },
        "end": {
          "line": 23,
          "column": 86
        }
      }
    },
    {
      "type": {
        "label": "name",
        "beforeExpr": false,
        "startsExpr": true,
        "rightAssociative": false,
        "isLoop": false,
        "isAssign": false,
        "prefix": false,
        "postfix": false,
        "binop": null
      },
      "value": "pattern",
      "start": 504,
      "end": 511,
      "loc": {
        "start": {
          "line": 23,
          "column": 86
        },
        "end": {
          "line": 23,
          "column": 93
        }
      }
    },
    {
      "type": {
        "label": ",",
        "beforeExpr": true,
        "startsExpr": false,
        "rightAssociative": false,
        "isLoop": false,
        "isAssign": false,
        "prefix": false,
        "postfix": false,
        "binop": null,
        "updateContext": null
      },
      "start": 511,
      "end": 512,
      "loc": {
        "start": {
          "line": 23,
          "column": 93
        },
        "end": {
          "line": 23,
          "column": 94
        }
      }
    },
    {
      "type": {
        "label": "name",
        "beforeExpr": false,
        "startsExpr": true,
        "rightAssociative": false,
        "isLoop": false,
        "isAssign": false,
        "prefix": false,
        "postfix": false,
        "binop": null
      },
      "value": "transformation",
      "start": 513,
      "end": 527,
      "loc": {
        "start": {
          "line": 23,
          "column": 95
        },
        "end": {
          "line": 23,
          "column": 109
        }
      }
    },
    {
      "type": {
        "label": ")",
        "beforeExpr": false,
        "startsExpr": false,
        "rightAssociative": false,
        "isLoop": false,
        "isAssign": false,
        "prefix": false,
        "postfix": false,
        "binop": null
      },
      "start": 527,
      "end": 528,
      "loc": {
        "start": {
          "line": 23,
          "column": 109
        },
        "end": {
          "line": 23,
          "column": 110
        }
      }
    },
    {
      "type": {
        "label": ")",
        "beforeExpr": false,
        "startsExpr": false,
        "rightAssociative": false,
        "isLoop": false,
        "isAssign": false,
        "prefix": false,
        "postfix": false,
        "binop": null
      },
      "start": 528,
      "end": 529,
      "loc": {
        "start": {
          "line": 23,
          "column": 110
        },
        "end": {
          "line": 23,
          "column": 111
        }
      }
    },
    {
      "type": {
        "label": ")",
        "beforeExpr": false,
        "startsExpr": false,
        "rightAssociative": false,
        "isLoop": false,
        "isAssign": false,
        "prefix": false,
        "postfix": false,
        "binop": null
      },
      "start": 529,
      "end": 530,
      "loc": {
        "start": {
          "line": 23,
          "column": 111
        },
        "end": {
          "line": 23,
          "column": 112
        }
      }
    },
    {
      "type": {
        "label": ";",
        "beforeExpr": true,
        "startsExpr": false,
        "rightAssociative": false,
        "isLoop": false,
        "isAssign": false,
        "prefix": false,
        "postfix": false,
        "binop": null,
        "updateContext": null
      },
      "start": 530,
      "end": 531,
      "loc": {
        "start": {
          "line": 23,
          "column": 112
        },
        "end": {
          "line": 23,
          "column": 113
        }
      }
    },
    {
      "type": {
        "label": "}",
        "beforeExpr": false,
        "startsExpr": false,
        "rightAssociative": false,
        "isLoop": false,
        "isAssign": false,
        "prefix": false,
        "postfix": false,
        "binop": null
      },
      "start": 536,
      "end": 537,
      "loc": {
        "start": {
          "line": 24,
          "column": 4
        },
        "end": {
          "line": 24,
          "column": 5
        }
      }
    },
    {
      "type": {
        "label": "}",
        "beforeExpr": false,
        "startsExpr": false,
        "rightAssociative": false,
        "isLoop": false,
        "isAssign": false,
        "prefix": false,
        "postfix": false,
        "binop": null
      },
      "start": 538,
      "end": 539,
      "loc": {
        "start": {
          "line": 25,
          "column": 0
        },
        "end": {
          "line": 25,
          "column": 1
        }
      }
    },
    {
      "type": {
        "label": "eof",
        "beforeExpr": false,
        "startsExpr": false,
        "rightAssociative": false,
        "isLoop": false,
        "isAssign": false,
        "prefix": false,
        "postfix": false,
        "binop": null,
        "updateContext": null
      },
      "start": 540,
      "end": 540,
      "loc": {
        "start": {
          "line": 26,
          "column": 0
        },
        "end": {
          "line": 26,
          "column": 0
        }
      }
    }
  ]
}