{
  "type": "File",
  "start": 0,
  "end": 676,
  "loc": {
    "start": {
      "line": 1,
      "column": 0
    },
    "end": {
      "line": 32,
      "column": 0
    }
  },
  "program": {
    "type": "Program",
    "start": 0,
    "end": 676,
    "loc": {
      "start": {
        "line": 1,
        "column": 0
      },
      "end": {
        "line": 32,
        "column": 0
      }
    },
    "sourceType": "module",
    "body": [
      {
        "type": "ImportDeclaration",
        "start": 0,
        "end": 40,
        "loc": {
          "start": {
            "line": 1,
            "column": 0
          },
          "end": {
            "line": 1,
            "column": 40
          }
        },
        "specifiers": [
          {
            "type": "ImportSpecifier",
            "start": 9,
            "end": 18,
            "loc": {
              "start": {
                "line": 1,
                "column": 9
              },
              "end": {
                "line": 1,
                "column": 18
              }
            },
            "imported": {
              "type": "Identifier",
              "start": 9,
              "end": 18,
              "loc": {
                "start": {
                  "line": 1,
                  "column": 9
                },
                "end": {
                  "line": 1,
                  "column": 18
                },
                "identifierName": "Predicate"
              },
              "name": "Predicate"
            },
            "local": {
              "type": "Identifier",
              "start": 9,
              "end": 18,
              "loc": {
                "start": {
                  "line": 1,
                  "column": 9
                },
                "end": {
                  "line": 1,
                  "column": 18
                },
                "identifierName": "Predicate"
              },
              "name": "Predicate"
            }
          }
        ],
        "source": {
          "type": "StringLiteral",
          "start": 26,
          "end": 39,
          "loc": {
            "start": {
              "line": 1,
              "column": 26
            },
            "end": {
              "line": 1,
              "column": 39
            }
          },
          "extra": {
            "rawValue": "./Predicate",
            "raw": "'./Predicate'"
          },
          "value": "./Predicate"
        },
        "trailingComments": [
          {
            "type": "CommentBlock",
            "value": "*\n * @desc\n * undefined\n * @lineNumber\n * 19\n * @param\n * {string} suffix\n * @return\n * {Predicate}\n ",
            "start": 41,
            "end": 146,
            "loc": {
              "start": {
                "line": 2,
                "column": 0
              },
              "end": {
                "line": 11,
                "column": 3
              }
            }
          },
          {
            "type": "CommentBlock",
            "value": "*\n * @desc Ensures that the `value` ends with a given suffix.\n *\n * @example\n * import { endsWith, ensure, TinyType } from 'tiny-types';\n *\n * class TextFileName extends TinyType {\n *     constructor(public readonly value: string) {\n *         super();\n *\n *         ensure('TextFileName', value, endsWith('.txt'));\n *     }\n * }\n *\n * @returns {Predicate<string>}\n ",
            "start": 147,
            "end": 517,
            "loc": {
              "start": {
                "line": 12,
                "column": 0
              },
              "end": {
                "line": 27,
                "column": 3
              }
            }
          }
        ]
      },
      {
        "type": "ExportNamedDeclaration",
        "start": 518,
        "end": 675,
        "loc": {
          "start": {
            "line": 28,
            "column": 0
          },
          "end": {
            "line": 31,
            "column": 1
          }
        },
        "specifiers": [],
        "source": null,
        "declaration": {
          "type": "FunctionDeclaration",
          "start": 525,
          "end": 675,
          "loc": {
            "start": {
              "line": 28,
              "column": 7
            },
            "end": {
              "line": 31,
              "column": 1
            }
          },
          "id": {
            "type": "Identifier",
            "start": 534,
            "end": 542,
            "loc": {
              "start": {
                "line": 28,
                "column": 16
              },
              "end": {
                "line": 28,
                "column": 24
              },
              "identifierName": "endsWith"
            },
            "name": "endsWith",
            "leadingComments": null
          },
          "generator": false,
          "expression": false,
          "async": false,
          "params": [
            {
              "type": "Identifier",
              "start": 543,
              "end": 549,
              "loc": {
                "start": {
                  "line": 28,
                  "column": 25
                },
                "end": {
                  "line": 28,
                  "column": 31
                },
                "identifierName": "suffix"
              },
              "name": "suffix"
            }
          ],
          "body": {
            "type": "BlockStatement",
            "start": 551,
            "end": 675,
            "loc": {
              "start": {
                "line": 28,
                "column": 33
              },
              "end": {
                "line": 31,
                "column": 1
              }
            },
            "body": [
              {
                "type": "ReturnStatement",
                "start": 557,
                "end": 673,
                "loc": {
                  "start": {
                    "line": 29,
                    "column": 4
                  },
                  "end": {
                    "line": 30,
                    "column": 35
                  }
                },
                "argument": {
                  "type": "CallExpression",
                  "start": 564,
                  "end": 672,
                  "loc": {
                    "start": {
                      "line": 29,
                      "column": 11
                    },
                    "end": {
                      "line": 30,
                      "column": 34
                    }
                  },
                  "callee": {
                    "type": "MemberExpression",
                    "start": 564,
                    "end": 576,
                    "loc": {
                      "start": {
                        "line": 29,
                        "column": 11
                      },
                      "end": {
                        "line": 29,
                        "column": 23
                      }
                    },
                    "object": {
                      "type": "Identifier",
                      "start": 564,
                      "end": 573,
                      "loc": {
                        "start": {
                          "line": 29,
                          "column": 11
                        },
                        "end": {
                          "line": 29,
                          "column": 20
                        },
                        "identifierName": "Predicate"
                      },
                      "name": "Predicate"
                    },
                    "property": {
                      "type": "Identifier",
                      "start": 574,
                      "end": 576,
                      "loc": {
                        "start": {
                          "line": 29,
                          "column": 21
                        },
                        "end": {
                          "line": 29,
                          "column": 23
                        },
                        "identifierName": "to"
                      },
                      "name": "to"
                    },
                    "computed": false
                  },
                  "arguments": [
                    {
                      "type": "TemplateLiteral",
                      "start": 577,
                      "end": 599,
                      "loc": {
                        "start": {
                          "line": 29,
                          "column": 24
                        },
                        "end": {
                          "line": 29,
                          "column": 46
                        }
                      },
                      "expressions": [
                        {
                          "type": "Identifier",
                          "start": 590,
                          "end": 596,
                          "loc": {
                            "start": {
                              "line": 29,
                              "column": 37
                            },
                            "end": {
                              "line": 29,
                              "column": 43
                            },
                            "identifierName": "suffix"
                          },
                          "name": "suffix"
                        }
                      ],
                      "quasis": [
                        {
                          "type": "TemplateElement",
                          "start": 578,
                          "end": 588,
                          "loc": {
                            "start": {
                              "line": 29,
                              "column": 25
                            },
                            "end": {
                              "line": 29,
                              "column": 35
                            }
                          },
                          "value": {
                            "raw": "end with '",
                            "cooked": "end with '"
                          },
                          "tail": false
                        },
                        {
                          "type": "TemplateElement",
                          "start": 597,
                          "end": 598,
                          "loc": {
                            "start": {
                              "line": 29,
                              "column": 44
                            },
                            "end": {
                              "line": 29,
                              "column": 45
                            }
                          },
                          "value": {
                            "raw": "'",
                            "cooked": "'"
                          },
                          "tail": true
                        }
                      ]
                    },
                    {
                      "type": "ArrowFunctionExpression",
                      "start": 601,
                      "end": 671,
                      "loc": {
                        "start": {
                          "line": 29,
                          "column": 48
                        },
                        "end": {
                          "line": 30,
                          "column": 33
                        }
                      },
                      "id": null,
                      "generator": false,
                      "expression": true,
                      "async": false,
                      "params": [
                        {
                          "type": "Identifier",
                          "start": 602,
                          "end": 607,
                          "loc": {
                            "start": {
                              "line": 29,
                              "column": 49
                            },
                            "end": {
                              "line": 29,
                              "column": 54
                            },
                            "identifierName": "value"
                          },
                          "name": "value"
                        }
                      ],
                      "body": {
                        "type": "LogicalExpression",
                        "start": 612,
                        "end": 671,
                        "loc": {
                          "start": {
                            "line": 29,
                            "column": 59
                          },
                          "end": {
                            "line": 30,
                            "column": 33
                          }
                        },
                        "left": {
                          "type": "BinaryExpression",
                          "start": 612,
                          "end": 637,
                          "loc": {
                            "start": {
                              "line": 29,
                              "column": 59
                            },
                            "end": {
                              "line": 29,
                              "column": 84
                            }
                          },
                          "left": {
                            "type": "UnaryExpression",
                            "start": 612,
                            "end": 624,
                            "loc": {
                              "start": {
                                "line": 29,
                                "column": 59
                              },
                              "end": {
                                "line": 29,
                                "column": 71
                              }
                            },
                            "operator": "typeof",
                            "prefix": true,
                            "argument": {
                              "type": "Identifier",
                              "start": 619,
                              "end": 624,
                              "loc": {
                                "start": {
                                  "line": 29,
                                  "column": 66
                                },
                                "end": {
                                  "line": 29,
                                  "column": 71
                                },
                                "identifierName": "value"
                              },
                              "name": "value"
                            },
                            "extra": {
                              "parenthesizedArgument": false
                            }
                          },
                          "operator": "===",
                          "right": {
                            "type": "StringLiteral",
                            "start": 629,
                            "end": 637,
                            "loc": {
                              "start": {
                                "line": 29,
                                "column": 76
                              },
                              "end": {
                                "line": 29,
                                "column": 84
                              }
                            },
                            "extra": {
                              "rawValue": "string",
                              "raw": "'string'"
                            },
                            "value": "string"
                          }
                        },
                        "operator": "&&",
                        "right": {
                          "type": "CallExpression",
                          "start": 649,
                          "end": 671,
                          "loc": {
                            "start": {
                              "line": 30,
                              "column": 11
                            },
                            "end": {
                              "line": 30,
                              "column": 33
                            }
                          },
                          "callee": {
                            "type": "MemberExpression",
                            "start": 649,
                            "end": 663,
                            "loc": {
                              "start": {
                                "line": 30,
                                "column": 11
                              },
                              "end": {
                                "line": 30,
                                "column": 25
                              }
                            },
                            "object": {
                              "type": "Identifier",
                              "start": 649,
                              "end": 654,
                              "loc": {
                                "start": {
                                  "line": 30,
                                  "column": 11
                                },
                                "end": {
                                  "line": 30,
                                  "column": 16
                                },
                                "identifierName": "value"
                              },
                              "name": "value"
                            },
                            "property": {
                              "type": "Identifier",
                              "start": 655,
                              "end": 663,
                              "loc": {
                                "start": {
                                  "line": 30,
                                  "column": 17
                                },
                                "end": {
                                  "line": 30,
                                  "column": 25
                                },
                                "identifierName": "endsWith"
                              },
                              "name": "endsWith"
                            },
                            "computed": false
                          },
                          "arguments": [
                            {
                              "type": "Identifier",
                              "start": 664,
                              "end": 670,
                              "loc": {
                                "start": {
                                  "line": 30,
                                  "column": 26
                                },
                                "end": {
                                  "line": 30,
                                  "column": 32
                                },
                                "identifierName": "suffix"
                              },
                              "name": "suffix"
                            }
                          ]
                        }
                      }
                    }
                  ]
                }
              }
            ],
            "directives": []
          },
          "leadingComments": [
            {
              "type": "CommentBlock",
              "value": "*\n * @desc\n * undefined\n * @lineNumber\n * 19\n * @param\n * {string} suffix\n * @return\n * {Predicate}\n ",
              "start": 41,
              "end": 146,
              "loc": {
                "start": {
                  "line": 2,
                  "column": 0
                },
                "end": {
                  "line": 11,
                  "column": 3
                }
              }
            },
            {
              "type": "CommentBlock",
              "value": "*\n * @desc Ensures that the `value` ends with a given suffix.\n *\n * @example\n * import { endsWith, ensure, TinyType } from 'tiny-types';\n *\n * class TextFileName extends TinyType {\n *     constructor(public readonly value: string) {\n *         super();\n *\n *         ensure('TextFileName', value, endsWith('.txt'));\n *     }\n * }\n *\n * @returns {Predicate<string>}\n ",
              "start": 147,
              "end": 517,
              "loc": {
                "start": {
                  "line": 12,
                  "column": 0
                },
                "end": {
                  "line": 27,
                  "column": 3
                }
              }
            }
          ],
          "trailingComments": []
        },
        "leadingComments": [
          {
            "type": "CommentBlock",
            "value": "*\n * @desc\n * undefined\n * @lineNumber\n * 19\n * @param\n * {string} suffix\n * @return\n * {Predicate}\n ",
            "start": 41,
            "end": 146,
            "loc": {
              "start": {
                "line": 2,
                "column": 0
              },
              "end": {
                "line": 11,
                "column": 3
              }
            }
          },
          {
            "type": "CommentBlock",
            "value": "*\n * @desc Ensures that the `value` ends with a given suffix.\n *\n * @example\n * import { endsWith, ensure, TinyType } from 'tiny-types';\n *\n * class TextFileName extends TinyType {\n *     constructor(public readonly value: string) {\n *         super();\n *\n *         ensure('TextFileName', value, endsWith('.txt'));\n *     }\n * }\n *\n * @returns {Predicate<string>}\n ",
            "start": 147,
            "end": 517,
            "loc": {
              "start": {
                "line": 12,
                "column": 0
              },
              "end": {
                "line": 27,
                "column": 3
              }
            }
          }
        ]
      }
    ],
    "directives": []
  },
  "comments": [
    {
      "type": "CommentBlock",
      "value": "*\n * @desc\n * undefined\n * @lineNumber\n * 19\n * @param\n * {string} suffix\n * @return\n * {Predicate}\n ",
      "start": 41,
      "end": 146,
      "loc": {
        "start": {
          "line": 2,
          "column": 0
        },
        "end": {
          "line": 11,
          "column": 3
        }
      }
    },
    {
      "type": "CommentBlock",
      "value": "*\n * @desc Ensures that the `value` ends with a given suffix.\n *\n * @example\n * import { endsWith, ensure, TinyType } from 'tiny-types';\n *\n * class TextFileName extends TinyType {\n *     constructor(public readonly value: string) {\n *         super();\n *\n *         ensure('TextFileName', value, endsWith('.txt'));\n *     }\n * }\n *\n * @returns {Predicate<string>}\n ",
      "start": 147,
      "end": 517,
      "loc": {
        "start": {
          "line": 12,
          "column": 0
        },
        "end": {
          "line": 27,
          "column": 3
        }
      }
    }
  ],
  "tokens": [
    {
      "type": {
        "label": "import",
        "keyword": "import",
        "beforeExpr": false,
        "startsExpr": true,
        "rightAssociative": false,
        "isLoop": false,
        "isAssign": false,
        "prefix": false,
        "postfix": false,
        "binop": null,
        "updateContext": null
      },
      "value": "import",
      "start": 0,
      "end": 6,
      "loc": {
        "start": {
          "line": 1,
          "column": 0
        },
        "end": {
          "line": 1,
          "column": 6
        }
      }
    },
    {
      "type": {
        "label": "{",
        "beforeExpr": true,
        "startsExpr": true,
        "rightAssociative": false,
        "isLoop": false,
        "isAssign": false,
        "prefix": false,
        "postfix": false,
        "binop": null
      },
      "start": 7,
      "end": 8,
      "loc": {
        "start": {
          "line": 1,
          "column": 7
        },
        "end": {
          "line": 1,
          "column": 8
        }
      }
    },
    {
      "type": {
        "label": "name",
        "beforeExpr": false,
        "startsExpr": true,
        "rightAssociative": false,
        "isLoop": false,
        "isAssign": false,
        "prefix": false,
        "postfix": false,
        "binop": null
      },
      "value": "Predicate",
      "start": 9,
      "end": 18,
      "loc": {
        "start": {
          "line": 1,
          "column": 9
        },
        "end": {
          "line": 1,
          "column": 18
        }
      }
    },
    {
      "type": {
        "label": "}",
        "beforeExpr": false,
        "startsExpr": false,
        "rightAssociative": false,
        "isLoop": false,
        "isAssign": false,
        "prefix": false,
        "postfix": false,
        "binop": null
      },
      "start": 19,
      "end": 20,
      "loc": {
        "start": {
          "line": 1,
          "column": 19
        },
        "end": {
          "line": 1,
          "column": 20
        }
      }
    },
    {
      "type": {
        "label": "name",
        "beforeExpr": false,
        "startsExpr": true,
        "rightAssociative": false,
        "isLoop": false,
        "isAssign": false,
        "prefix": false,
        "postfix": false,
        "binop": null
      },
      "value": "from",
      "start": 21,
      "end": 25,
      "loc": {
        "start": {
          "line": 1,
          "column": 21
        },
        "end": {
          "line": 1,
          "column": 25
        }
      }
    },
    {
      "type": {
        "label": "string",
        "beforeExpr": false,
        "startsExpr": true,
        "rightAssociative": false,
        "isLoop": false,
        "isAssign": false,
        "prefix": false,
        "postfix": false,
        "binop": null,
        "updateContext": null
      },
      "value": "./Predicate",
      "start": 26,
      "end": 39,
      "loc": {
        "start": {
          "line": 1,
          "column": 26
        },
        "end": {
          "line": 1,
          "column": 39
        }
      }
    },
    {
      "type": {
        "label": ";",
        "beforeExpr": true,
        "startsExpr": false,
        "rightAssociative": false,
        "isLoop": false,
        "isAssign": false,
        "prefix": false,
        "postfix": false,
        "binop": null,
        "updateContext": null
      },
      "start": 39,
      "end": 40,
      "loc": {
        "start": {
          "line": 1,
          "column": 39
        },
        "end": {
          "line": 1,
          "column": 40
        }
      }
    },
    {
      "type": "CommentBlock",
      "value": "*\n * @desc\n * undefined\n * @lineNumber\n * 19\n * @param\n * {string} suffix\n * @return\n * {Predicate}\n ",
      "start": 41,
      "end": 146,
      "loc": {
        "start": {
          "line": 2,
          "column": 0
        },
        "end": {
          "line": 11,
          "column": 3
        }
      }
    },
    {
      "type": "CommentBlock",
      "value": "*\n * @desc Ensures that the `value` ends with a given suffix.\n *\n * @example\n * import { endsWith, ensure, TinyType } from 'tiny-types';\n *\n * class TextFileName extends TinyType {\n *     constructor(public readonly value: string) {\n *         super();\n *\n *         ensure('TextFileName', value, endsWith('.txt'));\n *     }\n * }\n *\n * @returns {Predicate<string>}\n ",
      "start": 147,
      "end": 517,
      "loc": {
        "start": {
          "line": 12,
          "column": 0
        },
        "end": {
          "line": 27,
          "column": 3
        }
      }
    },
    {
      "type": {
        "label": "export",
        "keyword": "export",
        "beforeExpr": false,
        "startsExpr": false,
        "rightAssociative": false,
        "isLoop": false,
        "isAssign": false,
        "prefix": false,
        "postfix": false,
        "binop": null,
        "updateContext": null
      },
      "value": "export",
      "start": 518,
      "end": 524,
      "loc": {
        "start": {
          "line": 28,
          "column": 0
        },
        "end": {
          "line": 28,
          "column": 6
        }
      }
    },
    {
      "type": {
        "label": "function",
        "keyword": "function",
        "beforeExpr": false,
        "startsExpr": true,
        "rightAssociative": false,
        "isLoop": false,
        "isAssign": false,
        "prefix": false,
        "postfix": false,
        "binop": null
      },
      "value": "function",
      "start": 525,
      "end": 533,
      "loc": {
        "start": {
          "line": 28,
          "column": 7
        },
        "end": {
          "line": 28,
          "column": 15
        }
      }
    },
    {
      "type": {
        "label": "name",
        "beforeExpr": false,
        "startsExpr": true,
        "rightAssociative": false,
        "isLoop": false,
        "isAssign": false,
        "prefix": false,
        "postfix": false,
        "binop": null
      },
      "value": "endsWith",
      "start": 534,
      "end": 542,
      "loc": {
        "start": {
          "line": 28,
          "column": 16
        },
        "end": {
          "line": 28,
          "column": 24
        }
      }
    },
    {
      "type": {
        "label": "(",
        "beforeExpr": true,
        "startsExpr": true,
        "rightAssociative": false,
        "isLoop": false,
        "isAssign": false,
        "prefix": false,
        "postfix": false,
        "binop": null
      },
      "start": 542,
      "end": 543,
      "loc": {
        "start": {
          "line": 28,
          "column": 24
        },
        "end": {
          "line": 28,
          "column": 25
        }
      }
    },
    {
      "type": {
        "label": "name",
        "beforeExpr": false,
        "startsExpr": true,
        "rightAssociative": false,
        "isLoop": false,
        "isAssign": false,
        "prefix": false,
        "postfix": false,
        "binop": null
      },
      "value": "suffix",
      "start": 543,
      "end": 549,
      "loc": {
        "start": {
          "line": 28,
          "column": 25
        },
        "end": {
          "line": 28,
          "column": 31
        }
      }
    },
    {
      "type": {
        "label": ")",
        "beforeExpr": false,
        "startsExpr": false,
        "rightAssociative": false,
        "isLoop": false,
        "isAssign": false,
        "prefix": false,
        "postfix": false,
        "binop": null
      },
      "start": 549,
      "end": 550,
      "loc": {
        "start": {
          "line": 28,
          "column": 31
        },
        "end": {
          "line": 28,
          "column": 32
        }
      }
    },
    {
      "type": {
        "label": "{",
        "beforeExpr": true,
        "startsExpr": true,
        "rightAssociative": false,
        "isLoop": false,
        "isAssign": false,
        "prefix": false,
        "postfix": false,
        "binop": null
      },
      "start": 551,
      "end": 552,
      "loc": {
        "start": {
          "line": 28,
          "column": 33
        },
        "end": {
          "line": 28,
          "column": 34
        }
      }
    },
    {
      "type": {
        "label": "return",
        "keyword": "return",
        "beforeExpr": true,
        "startsExpr": false,
        "rightAssociative": false,
        "isLoop": false,
        "isAssign": false,
        "prefix": false,
        "postfix": false,
        "binop": null,
        "updateContext": null
      },
      "value": "return",
      "start": 557,
      "end": 563,
      "loc": {
        "start": {
          "line": 29,
          "column": 4
        },
        "end": {
          "line": 29,
          "column": 10
        }
      }
    },
    {
      "type": {
        "label": "name",
        "beforeExpr": false,
        "startsExpr": true,
        "rightAssociative": false,
        "isLoop": false,
        "isAssign": false,
        "prefix": false,
        "postfix": false,
        "binop": null
      },
      "value": "Predicate",
      "start": 564,
      "end": 573,
      "loc": {
        "start": {
          "line": 29,
          "column": 11
        },
        "end": {
          "line": 29,
          "column": 20
        }
      }
    },
    {
      "type": {
        "label": ".",
        "beforeExpr": false,
        "startsExpr": false,
        "rightAssociative": false,
        "isLoop": false,
        "isAssign": false,
        "prefix": false,
        "postfix": false,
        "binop": null,
        "updateContext": null
      },
      "start": 573,
      "end": 574,
      "loc": {
        "start": {
          "line": 29,
          "column": 20
        },
        "end": {
          "line": 29,
          "column": 21
        }
      }
    },
    {
      "type": {
        "label": "name",
        "beforeExpr": false,
        "startsExpr": true,
        "rightAssociative": false,
        "isLoop": false,
        "isAssign": false,
        "prefix": false,
        "postfix": false,
        "binop": null
      },
      "value": "to",
      "start": 574,
      "end": 576,
      "loc": {
        "start": {
          "line": 29,
          "column": 21
        },
        "end": {
          "line": 29,
          "column": 23
        }
      }
    },
    {
      "type": {
        "label": "(",
        "beforeExpr": true,
        "startsExpr": true,
        "rightAssociative": false,
        "isLoop": false,
        "isAssign": false,
        "prefix": false,
        "postfix": false,
        "binop": null
      },
      "start": 576,
      "end": 577,
      "loc": {
        "start": {
          "line": 29,
          "column": 23
        },
        "end": {
          "line": 29,
          "column": 24
        }
      }
    },
    {
      "type": {
        "label": "`",
        "beforeExpr": false,
        "startsExpr": true,
        "rightAssociative": false,
        "isLoop": false,
        "isAssign": false,
        "prefix": false,
        "postfix": false,
        "binop": null
      },
      "start": 577,
      "end": 578,
      "loc": {
        "start": {
          "line": 29,
          "column": 24
        },
        "end": {
          "line": 29,
          "column": 25
        }
      }
    },
    {
      "type": {
        "label": "template",
        "beforeExpr": false,
        "startsExpr": false,
        "rightAssociative": false,
        "isLoop": false,
        "isAssign": false,
        "prefix": false,
        "postfix": false,
        "binop": null,
        "updateContext": null
      },
      "value": "end with '",
      "start": 578,
      "end": 588,
      "loc": {
        "start": {
          "line": 29,
          "column": 25
        },
        "end": {
          "line": 29,
          "column": 35
        }
      }
    },
    {
      "type": {
        "label": "${",
        "beforeExpr": true,
        "startsExpr": true,
        "rightAssociative": false,
        "isLoop": false,
        "isAssign": false,
        "prefix": false,
        "postfix": false,
        "binop": null
      },
      "start": 588,
      "end": 590,
      "loc": {
        "start": {
          "line": 29,
          "column": 35
        },
        "end": {
          "line": 29,
          "column": 37
        }
      }
    },
    {
      "type": {
        "label": "name",
        "beforeExpr": false,
        "startsExpr": true,
        "rightAssociative": false,
        "isLoop": false,
        "isAssign": false,
        "prefix": false,
        "postfix": false,
        "binop": null
      },
      "value": "suffix",
      "start": 590,
      "end": 596,
      "loc": {
        "start": {
          "line": 29,
          "column": 37
        },
        "end": {
          "line": 29,
          "column": 43
        }
      }
    },
    {
      "type": {
        "label": "}",
        "beforeExpr": false,
        "startsExpr": false,
        "rightAssociative": false,
        "isLoop": false,
        "isAssign": false,
        "prefix": false,
        "postfix": false,
        "binop": null
      },
      "start": 596,
      "end": 597,
      "loc": {
        "start": {
          "line": 29,
          "column": 43
        },
        "end": {
          "line": 29,
          "column": 44
        }
      }
    },
    {
      "type": {
        "label": "template",
        "beforeExpr": false,
        "startsExpr": false,
        "rightAssociative": false,
        "isLoop": false,
        "isAssign": false,
        "prefix": false,
        "postfix": false,
        "binop": null,
        "updateContext": null
      },
      "value": "'",
      "start": 597,
      "end": 598,
      "loc": {
        "start": {
          "line": 29,
          "column": 44
        },
        "end": {
          "line": 29,
          "column": 45
        }
      }
    },
    {
      "type": {
        "label": "`",
        "beforeExpr": false,
        "startsExpr": true,
        "rightAssociative": false,
        "isLoop": false,
        "isAssign": false,
        "prefix": false,
        "postfix": false,
        "binop": null
      },
      "start": 598,
      "end": 599,
      "loc": {
        "start": {
          "line": 29,
          "column": 45
        },
        "end": {
          "line": 29,
          "column": 46
        }
      }
    },
    {
      "type": {
        "label": ",",
        "beforeExpr": true,
        "startsExpr": false,
        "rightAssociative": false,
        "isLoop": false,
        "isAssign": false,
        "prefix": false,
        "postfix": false,
        "binop": null,
        "updateContext": null
      },
      "start": 599,
      "end": 600,
      "loc": {
        "start": {
          "line": 29,
          "column": 46
        },
        "end": {
          "line": 29,
          "column": 47
        }
      }
    },
    {
      "type": {
        "label": "(",
        "beforeExpr": true,
        "startsExpr": true,
        "rightAssociative": false,
        "isLoop": false,
        "isAssign": false,
        "prefix": false,
        "postfix": false,
        "binop": null
      },
      "start": 601,
      "end": 602,
      "loc": {
        "start": {
          "line": 29,
          "column": 48
        },
        "end": {
          "line": 29,
          "column": 49
        }
      }
    },
    {
      "type": {
        "label": "name",
        "beforeExpr": false,
        "startsExpr": true,
        "rightAssociative": false,
        "isLoop": false,
        "isAssign": false,
        "prefix": false,
        "postfix": false,
        "binop": null
      },
      "value": "value",
      "start": 602,
      "end": 607,
      "loc": {
        "start": {
          "line": 29,
          "column": 49
        },
        "end": {
          "line": 29,
          "column": 54
        }
      }
    },
    {
      "type": {
        "label": ")",
        "beforeExpr": false,
        "startsExpr": false,
        "rightAssociative": false,
        "isLoop": false,
        "isAssign": false,
        "prefix": false,
        "postfix": false,
        "binop": null
      },
      "start": 607,
      "end": 608,
      "loc": {
        "start": {
          "line": 29,
          "column": 54
        },
        "end": {
          "line": 29,
          "column": 55
        }
      }
    },
    {
      "type": {
        "label": "=>",
        "beforeExpr": true,
        "startsExpr": false,
        "rightAssociative": false,
        "isLoop": false,
        "isAssign": false,
        "prefix": false,
        "postfix": false,
        "binop": null,
        "updateContext": null
      },
      "start": 609,
      "end": 611,
      "loc": {
        "start": {
          "line": 29,
          "column": 56
        },
        "end": {
          "line": 29,
          "column": 58
        }
      }
    },
    {
      "type": {
        "label": "typeof",
        "keyword": "typeof",
        "beforeExpr": true,
        "startsExpr": true,
        "rightAssociative": false,
        "isLoop": false,
        "isAssign": false,
        "prefix": true,
        "postfix": false,
        "binop": null,
        "updateContext": null
      },
      "value": "typeof",
      "start": 612,
      "end": 618,
      "loc": {
        "start": {
          "line": 29,
          "column": 59
        },
        "end": {
          "line": 29,
          "column": 65
        }
      }
    },
    {
      "type": {
        "label": "name",
        "beforeExpr": false,
        "startsExpr": true,
        "rightAssociative": false,
        "isLoop": false,
        "isAssign": false,
        "prefix": false,
        "postfix": false,
        "binop": null
      },
      "value": "value",
      "start": 619,
      "end": 624,
      "loc": {
        "start": {
          "line": 29,
          "column": 66
        },
        "end": {
          "line": 29,
          "column": 71
        }
      }
    },
    {
      "type": {
        "label": "==/!=",
        "beforeExpr": true,
        "startsExpr": false,
        "rightAssociative": false,
        "isLoop": false,
        "isAssign": false,
        "prefix": false,
        "postfix": false,
        "binop": 6,
        "updateContext": null
      },
      "value": "===",
      "start": 625,
      "end": 628,
      "loc": {
        "start": {
          "line": 29,
          "column": 72
        },
        "end": {
          "line": 29,
          "column": 75
        }
      }
    },
    {
      "type": {
        "label": "string",
        "beforeExpr": false,
        "startsExpr": true,
        "rightAssociative": false,
        "isLoop": false,
        "isAssign": false,
        "prefix": false,
        "postfix": false,
        "binop": null,
        "updateContext": null
      },
      "value": "string",
      "start": 629,
      "end": 637,
      "loc": {
        "start": {
          "line": 29,
          "column": 76
        },
        "end": {
          "line": 29,
          "column": 84
        }
      }
    },
    {
      "type": {
        "label": "&&",
        "beforeExpr": true,
        "startsExpr": false,
        "rightAssociative": false,
        "isLoop": false,
        "isAssign": false,
        "prefix": false,
        "postfix": false,
        "binop": 2,
        "updateContext": null
      },
      "value": "&&",
      "start": 646,
      "end": 648,
      "loc": {
        "start": {
          "line": 30,
          "column": 8
        },
        "end": {
          "line": 30,
          "column": 10
        }
      }
    },
    {
      "type": {
        "label": "name",
        "beforeExpr": false,
        "startsExpr": true,
        "rightAssociative": false,
        "isLoop": false,
        "isAssign": false,
        "prefix": false,
        "postfix": false,
        "binop": null
      },
      "value": "value",
      "start": 649,
      "end": 654,
      "loc": {
        "start": {
          "line": 30,
          "column": 11
        },
        "end": {
          "line": 30,
          "column": 16
        }
      }
    },
    {
      "type": {
        "label": ".",
        "beforeExpr": false,
        "startsExpr": false,
        "rightAssociative": false,
        "isLoop": false,
        "isAssign": false,
        "prefix": false,
        "postfix": false,
        "binop": null,
        "updateContext": null
      },
      "start": 654,
      "end": 655,
      "loc": {
        "start": {
          "line": 30,
          "column": 16
        },
        "end": {
          "line": 30,
          "column": 17
        }
      }
    },
    {
      "type": {
        "label": "name",
        "beforeExpr": false,
        "startsExpr": true,
        "rightAssociative": false,
        "isLoop": false,
        "isAssign": false,
        "prefix": false,
        "postfix": false,
        "binop": null
      },
      "value": "endsWith",
      "start": 655,
      "end": 663,
      "loc": {
        "start": {
          "line": 30,
          "column": 17
        },
        "end": {
          "line": 30,
          "column": 25
        }
      }
    },
    {
      "type": {
        "label": "(",
        "beforeExpr": true,
        "startsExpr": true,
        "rightAssociative": false,
        "isLoop": false,
        "isAssign": false,
        "prefix": false,
        "postfix": false,
        "binop": null
      },
      "start": 663,
      "end": 664,
      "loc": {
        "start": {
          "line": 30,
          "column": 25
        },
        "end": {
          "line": 30,
          "column": 26
        }
      }
    },
    {
      "type": {
        "label": "name",
        "beforeExpr": false,
        "startsExpr": true,
        "rightAssociative": false,
        "isLoop": false,
        "isAssign": false,
        "prefix": false,
        "postfix": false,
        "binop": null
      },
      "value": "suffix",
      "start": 664,
      "end": 670,
      "loc": {
        "start": {
          "line": 30,
          "column": 26
        },
        "end": {
          "line": 30,
          "column": 32
        }
      }
    },
    {
      "type": {
        "label": ")",
        "beforeExpr": false,
        "startsExpr": false,
        "rightAssociative": false,
        "isLoop": false,
        "isAssign": false,
        "prefix": false,
        "postfix": false,
        "binop": null
      },
      "start": 670,
      "end": 671,
      "loc": {
        "start": {
          "line": 30,
          "column": 32
        },
        "end": {
          "line": 30,
          "column": 33
        }
      }
    },
    {
      "type": {
        "label": ")",
        "beforeExpr": false,
        "startsExpr": false,
        "rightAssociative": false,
        "isLoop": false,
        "isAssign": false,
        "prefix": false,
        "postfix": false,
        "binop": null
      },
      "start": 671,
      "end": 672,
      "loc": {
        "start": {
          "line": 30,
          "column": 33
        },
        "end": {
          "line": 30,
          "column": 34
        }
      }
    },
    {
      "type": {
        "label": ";",
        "beforeExpr": true,
        "startsExpr": false,
        "rightAssociative": false,
        "isLoop": false,
        "isAssign": false,
        "prefix": false,
        "postfix": false,
        "binop": null,
        "updateContext": null
      },
      "start": 672,
      "end": 673,
      "loc": {
        "start": {
          "line": 30,
          "column": 34
        },
        "end": {
          "line": 30,
          "column": 35
        }
      }
    },
    {
      "type": {
        "label": "}",
        "beforeExpr": false,
        "startsExpr": false,
        "rightAssociative": false,
        "isLoop": false,
        "isAssign": false,
        "prefix": false,
        "postfix": false,
        "binop": null
      },
      "start": 674,
      "end": 675,
      "loc": {
        "start": {
          "line": 31,
          "column": 0
        },
        "end": {
          "line": 31,
          "column": 1
        }
      }
    },
    {
      "type": {
        "label": "eof",
        "beforeExpr": false,
        "startsExpr": false,
        "rightAssociative": false,
        "isLoop": false,
        "isAssign": false,
        "prefix": false,
        "postfix": false,
        "binop": null,
        "updateContext": null
      },
      "start": 676,
      "end": 676,
      "loc": {
        "start": {
          "line": 32,
          "column": 0
        },
        "end": {
          "line": 32,
          "column": 0
        }
      }
    }
  ]
}